{"home":{"title":"Home","tiles":["instagram-printed-matter","ramble-hotel","audi-r8","summers-corner-journal","instagram-badges","laurus","instagram-nyc","factory-identity","corner-house-cafe","fling","factory-brand-book-v10","summers-corner-grand-opening","happybunny","factory-brand-book-v11","john-huet","live-for-this-fitness","summers-corner-feather","audi-printed-matter","cotton-blend","fresh-jets","true-blue","the-barre-standard","mode-set","aspen-x","callaway-technology-icon-system","summers-corner-ad","muse-studio","oakley-eyewear","roth","obrien","revo-press-kit","innofin","revo-brochure","audi-tdi","oakley-womens-campaign","pressery","summit-sky-ranch","revo-jimmy-chin","true-north","spanish-peaks","more-mavericks"],"body":"\n# Home\n","id":"home"}}